idrivetools/__init__.py
idrivetools/file_tools/__init__.py
idrivetools/file_tools/bmw_backup_file.py
idrivetools/file_tools/bmw_data_1_count_file.py
idrivetools/file_tools/bmw_data_1_file.py
idrivetools/file_tools/bmw_file.py
idrivetools/file_tools/bmw_file_factory.py
idrivetools/file_tools/bmw_info_file.py
idrivetools/file_tools/inverter.py
idrivetools/p1.py
idrivetools/p2.py
idrivetools/p3.py
idrivetools/process_files.py
idrivetools/test.py
idrivetools-0.1.28.dist-info/entry_points.txt
idrivetools-0.1.28.dist-info/WHEEL
idrivetools-0.1.28.dist-info/METADATA
idrivetools-0.1.28.dist-info/RECORD
