Metadata-Version: 2.1
Name: idrivetools
Version: 0.1.28
Summary: iDrive tools for packing and unpacking BMW backups
Home-page: https://github.com/Centurix/idrivetools
Keywords: bmw,idrive,media,backup,restore
Author: Chris Read
Author-email: centurix@gmail.com
Requires-Python: >=3.7,<4.0
Classifier: Development Status :: 4 - Beta
Classifier: Environment :: Console
Classifier: Intended Audience :: End Users/Desktop
Classifier: Natural Language :: English
Classifier: Operating System :: POSIX :: Linux
Classifier: Programming Language :: Python :: 3
Classifier: Programming Language :: Python :: 3.7
Classifier: Programming Language :: Python :: 3.8
Classifier: Topic :: Multimedia
Classifier: Topic :: Multimedia :: Sound/Audio
Classifier: Topic :: Multimedia :: Sound/Audio :: Conversion
Classifier: Topic :: Utilities
Requires-Dist: click (>=7.1.2,<8.0.0)
Project-URL: Repository, https://github.com/Centurix/idrivetools
